pendle_v2/__init__.py
pendle_v2/api/__init__.py
pendle_v2/api/assets/__init__.py
pendle_v2/api/assets/assets_controller_get_all_asset_prices_by_addresses.py
pendle_v2/api/assets/assets_controller_get_all_assets.py
pendle_v2/api/assets/assets_cross_chain_controller_get_all_assets_cross_chain.py
pendle_v2/api/assets_legacy/__init__.py
pendle_v2/api/assets_legacy/assets_controller_all_assets.py
pendle_v2/api/assets_legacy/assets_controller_all_assets_v_2.py
pendle_v2/api/assets_legacy/assets_controller_asset.py
pendle_v2/api/assets_legacy/assets_controller_assets.py
pendle_v2/api/assets_legacy/assets_controller_get_all_pendle_tokens_in_uniswap_format.py
pendle_v2/api/assets_legacy/sys_controller_asset_sy.py
pendle_v2/api/assets_legacy/sys_controller_whitelisted_sys.py
pendle_v2/api/chains_legacy/__init__.py
pendle_v2/api/chains_legacy/chains_controller_get_supported_chain_ids.py
pendle_v2/api/cross_pt/__init__.py
pendle_v2/api/cross_pt/cross_pt_controller_get_all_cross_pt.py
pendle_v2/api/dashboard/__init__.py
pendle_v2/api/dashboard/dashboard_controller_get_user_positions.py
pendle_v2/api/incentive_rewards/__init__.py
pendle_v2/api/incentive_rewards/incentive_rewards_controller_get_maker_incentive_distribution.py
pendle_v2/api/integrations/__init__.py
pendle_v2/api/integrations/integrations_controller_get_asset.py
pendle_v2/api/integrations/integrations_controller_get_events.py
pendle_v2/api/integrations/integrations_controller_get_latest_block.py
pendle_v2/api/integrations/integrations_controller_get_pair.py
pendle_v2/api/limit_orders/__init__.py
pendle_v2/api/limit_orders/limit_orders_controller_create_order.py
pendle_v2/api/limit_orders/limit_orders_controller_fetch_makers.py
pendle_v2/api/limit_orders/limit_orders_controller_generate_limit_order_data.py
pendle_v2/api/limit_orders/limit_orders_controller_get_all_archived_limit_orders.py
pendle_v2/api/limit_orders/limit_orders_controller_get_all_limit_orders.py
pendle_yield-0.1.0a2.dist-info/METADATA
pendle_yield-0.1.0a2.dist-info/WHEEL
pendle_yield-0.1.0a2.dist-info/entry_points.txt
pendle_yield-0.1.0a2.dist-info/RECORD
