Metadata-Version: 2.1
Name: pendle-yield
Version: 0.1.0a2
Summary: Python SDK for interacting with Pendle Finance data
Keywords: pendle,finance,defi,ethereum,blockchain,api,sdk
Author: obsh-onchain
License: MIT
Classifier: Development Status :: 3 - Alpha
Classifier: Intended Audience :: Developers
Classifier: Intended Audience :: Financial and Insurance Industry
Classifier: License :: OSI Approved :: MIT License
Classifier: Operating System :: OS Independent
Classifier: Programming Language :: Python :: 3
Classifier: Programming Language :: Python :: 3.11
Classifier: Programming Language :: Python :: 3.12
Classifier: Topic :: Office/Business :: Financial
Classifier: Topic :: Software Development :: Libraries :: Python Modules
Classifier: Topic :: Internet :: WWW/HTTP :: Dynamic Content
Project-URL: Homepage, https://github.com/obsh-onchain/pendle-yield
Project-URL: Repository, https://github.com/obsh-onchain/pendle-yield
Project-URL: Issues, https://github.com/obsh-onchain/pendle-yield/issues
Requires-Python: >=3.11
Requires-Dist: httpx>=0.25.0
Requires-Dist: pydantic>=2.0.0
Requires-Dist: attrs>=25.4.0
Requires-Dist: python-dateutil>=2.9.0.post0
Provides-Extra: dev
Requires-Dist: ruff>=0.1.0; extra == "dev"
Requires-Dist: mypy>=1.5.0; extra == "dev"
Requires-Dist: pytest>=7.4.0; extra == "dev"
Requires-Dist: types-requests>=2.31.0; extra == "dev"
Requires-Dist: openapi-python-client>=0.26.2; extra == "dev"
Provides-Extra: docs
Requires-Dist: mkdocs>=1.5.0; extra == "docs"
Requires-Dist: mkdocs-material>=9.0.0; extra == "docs"
Requires-Dist: mkdocstrings[python]>=0.23.0; extra == "docs"
